zorro/__init__.py
zorro/common.py
zorro/evaluate_ZS.py
zorro/operators.py
zorro/parse_zorroscript.py
zorro/price_cache.py
zorro/stockdata.py
zorroclient-0.0.1a0.dist-info/LICENSE
zorroclient-0.0.1a0.dist-info/METADATA
zorroclient-0.0.1a0.dist-info/WHEEL
zorroclient-0.0.1a0.dist-info/top_level.txt
zorroclient-0.0.1a0.dist-info/RECORD
