Metadata-Version: 2.1
Name: zorroclient
Version: 0.0.1a0
Summary: This client is a wrapper for the official Zorro API
Home-page: https://github.com/myfatemi04/webparsa
Author: Michael Fatemi, Suhas Nandiraju
Author-email: myfatemi04@gmail.com
License: UNKNOWN
Platform: UNKNOWN
Classifier: Programming Language :: Python :: 3
Classifier: License :: OSI Approved :: MIT License
Classifier: Operating System :: OS Independent
Requires-Python: >=3.6
Requires-Dist: requests
